setup.cfg
setup.py
AmbilightParty.egg-info/PKG-INFO
AmbilightParty.egg-info/SOURCES.txt
AmbilightParty.egg-info/dependency_links.txt
AmbilightParty.egg-info/entry_points.txt
AmbilightParty.egg-info/requires.txt
AmbilightParty.egg-info/top_level.txt
ambilight/__init__.py
ambilight/party.py
ambilight/tv.py
ambilight/tvbuff.py
ambilight/data/caterpillars.json
ambilight/data/flags.json