Metadata-Version: 1.0
Name: AmbilightParty
Version: 1.0
Summary: Have fun with your Philips Ambilight TV
Home-page: https://github.com/pascalif/AmbilightParty
Author: Pascalif
Author-email: UNKNOWN
License: GPL
Keywords: Ambilight Philips JointSpace television
Platform: UNKNOWN
